{
  "name": "revit_create_3d_view_from_sheet_click",
  "description": "Creates a perspective 3D view with its camera at a sheet click mapped through viewport transforms into model space.",
  "arguments": {
    "type": "object",
    "properties": {
      "viewport_id": {
        "type": "integer",
        "description": "Viewport element id on the active sheet"
      },
      "sheet_x": {
        "type": "number",
        "description": "X coordinate of the click in sheet space"
      },
      "sheet_y": {
        "type": "number",
        "description": "Y coordinate of the click in sheet space"
      }
    },
    "required": ["viewport_id", "sheet_x", "sheet_y"]
  },
  "commandClass": "Command",
  "sample": "SheetToView3D",
  "source": "src/SheetToView3D/CS/SheetToView3D.cs",
  "mcpRating": 5,
  "requiresUi": true,
  "notes": "MakeView3D.MakeFromViewportClick contains the logic; replace PickPoint with supplied coordinates."
}
